Metadata-Version: 2.1
Name: gameofcard
Version: 0.0.4.3
Summary: Just a humble implementation of different card games.
Home-page: https://github.com/EPgg92/gameofcard/archive/0.0.4.3
Author: EPgg92
Author-email: poggio.enzo@gmail.com
License: UNKNOWN
Download-URL: https://github.com/EPgg92/gameofcard/archive/0.0.4.3.tar.gz
Keywords: card game briscola
Platform: UNKNOWN
Classifier: Operating System :: OS Independent
Classifier: Programming Language :: Python :: 3
Classifier: Programming Language :: Python :: 3.8
